ruuvi_lapio/__init__.py
ruuvi_lapio/__main__.py
ruuvi_lapio/main.py
ruuvi_lapio/mock_sensor.py
ruuvi_lapio-0.3.1.dist-info/LICENSE
ruuvi_lapio-0.3.1.dist-info/METADATA
ruuvi_lapio-0.3.1.dist-info/WHEEL
ruuvi_lapio-0.3.1.dist-info/RECORD
