Metadata-Version: 2.1
Name: ruuvi-lapio
Version: 0.3.1
Summary: A simple app that sends sensory data over http
Home-page: https://github.com/poksiala/ruuvi-lapio
License: MIT
Author: Panu Oksiala
Author-email: panu@oksiala.fi
Requires-Python: >=3.7,<4.0
Classifier: License :: OSI Approved :: MIT License
Classifier: Programming Language :: Python :: 3
Classifier: Programming Language :: Python :: 3.7
Classifier: Programming Language :: Python :: 3.8
Classifier: Programming Language :: Python :: 3.9
Classifier: Programming Language :: Python :: 3.10
Classifier: Programming Language :: Python :: 3.11
Requires-Dist: aiohttp (>=3.8.1,<4.0.0)
Requires-Dist: ruuvitag-sensor (>=2.1.0,<3.0.0)
Project-URL: Repository, https://github.com/poksiala/ruuvi-lapio
